{
  "nextId": 7,
  "websites": [
    {
      "id": 1,
      "name": "GitHub",
      "url": "https://github.com",
      "date_added": "2024-01-10",
      "notes": "Code hosting platform"
    },
    {
      "id": 2,
      "name": "MDN Web Docs",
      "url": "https://developer.mozilla.org",
      "date_added": "2024-02-14",
      "notes": "Best web reference docs"
    },
    {
      "id": 3,
      "name": "Stack Overflow",
      "url": "https://stackoverflow.com",
      "date_added": "2024-03-05",
      "notes": "Q&A for developers"
    },
    {
      "id": 4,
      "name": "Hacker News",
      "url": "https://news.ycombinator.com",
      "date_added": "2024-04-20",
      "notes": "Tech news aggregator"
    },
    {
      "id": 5,
      "name": "Excalidraw",
      "url": "https://excalidraw.com",
      "date_added": "2024-05-01",
      "notes": "Whiteboard / diagrams tool"
    },
    {
      "id": 6,
      "name": "leetcode",
      "url": "https://leetcode.com",
      "date_added": "2026-03-22",
      "notes": "solved daily problem"
    }
  ]
}